defineif/__init__.py
defineif/defineif.py
defineif/meta.py
defineif/py.typed
defineif-0.1.0.dist-info/LICENSE
defineif-0.1.0.dist-info/METADATA
defineif-0.1.0.dist-info/WHEEL
defineif-0.1.0.dist-info/top_level.txt
defineif-0.1.0.dist-info/zip-safe
defineif-0.1.0.dist-info/RECORD
