Metadata-Version: 2.1
Name: defineif
Version: 0.1.0
Summary: attr: defineif.__description__
Home-page: https://defineif.hakancelik.dev/
Author: Hakan Çelik
Author-email: hakancelikdev@gmail.com
License: GPL-3.0
Project-URL: Documentation, https://defineif.hakancelik.dev/
Project-URL: Issues, https://github.com/hakancelikdev/defineif/issues/
Project-URL: Changelog, https://defineif.hakancelik.dev/changelog
Classifier: Development Status :: 1 - Planning
Classifier: Intended Audience :: Developers
Classifier: License :: OSI Approved :: GNU General Public License v3 (GPLv3)
Classifier: Operating System :: OS Independent
Classifier: Programming Language :: Python
Classifier: Programming Language :: Python :: 3
Classifier: Programming Language :: Python :: 3 :: Only
Classifier: Programming Language :: Python :: 3.6
Classifier: Programming Language :: Python :: 3.7
Classifier: Programming Language :: Python :: 3.8
Classifier: Programming Language :: Python :: 3.9
Classifier: Programming Language :: Python :: 3.10
Classifier: Programming Language :: Python :: 3.11
Classifier: Programming Language :: Python :: Implementation :: CPython
Classifier: Topic :: Software Development :: Libraries :: Python Modules
Requires-Python: >=3.6
License-File: LICENSE
Provides-Extra: docs
Requires-Dist: mkdocs (==1.3.0) ; extra == 'docs'
Requires-Dist: mkdocs-material (==8.3.6) ; extra == 'docs'
Requires-Dist: mkdocs-markdownextradata-plugin (==0.2.5) ; extra == 'docs'
Requires-Dist: mkdocs-minify-plugin (==0.5.0) ; extra == 'docs'
Requires-Dist: mkdocs-git-revision-date-localized-plugin (==1.0.1) ; extra == 'docs'
Provides-Extra: tests
Requires-Dist: pytest (==6.2.4) ; extra == 'tests'
Requires-Dist: pytest-cov (==2.12.1) ; extra == 'tests'
